MANIFEST.in
README.md
setup.cfg
setup.py
pug4py/__init__.py
pug4py/package.json
pug4py/pug.py
pug4py/pug_compile.js
pug4py/yarn.lock