Metadata-Version: 2.1
Name: pug4py
Version: 1.0.1
Summary: Pug4Py is a tool that allows you to integrate Pug js as a templating engine into any Python framework.
Home-page: https://github.com/multiversecoder/pug4py
Author: Adriano Romanazzo (multiversecoder)
Author-email: pythonmultiverse@gmx.com
License: MIT License
Download-URL: https://pypi.python.org/pypi/pug4py
Platform: UNKNOWN
Classifier: Development Status :: 5 - Production/Stable
Classifier: Intended Audience :: Developers
Classifier: Natural Language :: English
Classifier: License :: OSI Approved :: MIT License
Classifier: Programming Language :: Python
Classifier: Programming Language :: Python :: 3.7
Classifier: Programming Language :: Python :: 3.8
Classifier: Programming Language :: JavaScript
